agentcomms/__init__.py
agentcomms/adminpanel/__init__.py
agentcomms/adminpanel/constants.py
agentcomms/adminpanel/files.py
agentcomms/adminpanel/page.py
agentcomms/adminpanel/server.py
agentcomms/discord/__init__.py
agentcomms/discord/actions.py
agentcomms/discord/connector.py
agentcomms/twitter/__init__.py
agentcomms/twitter/actions.py
agentcomms/twitter/connector.py
agentcomms-0.2.3.dist-info/LICENSE
agentcomms-0.2.3.dist-info/METADATA
agentcomms-0.2.3.dist-info/WHEEL
agentcomms-0.2.3.dist-info/top_level.txt
agentcomms-0.2.3.dist-info/RECORD
