Metadata-Version: 2.1
Name: agentcomms
Version: 0.2.3
Summary: Social media connectors for agents
Home-page: https://github.com/AutonomousResearchGroup/agentcomms
Author: Moon
Author-email: shawmakesmagic@gmail.com
License: MIT
Classifier: Development Status :: 4 - Beta
Classifier: Intended Audience :: Science/Research
Classifier: License :: OSI Approved :: MIT License
Classifier: Operating System :: POSIX :: Linux
Classifier: Programming Language :: Python :: 3
Classifier: Operating System :: MacOS :: MacOS X
Classifier: Operating System :: Microsoft :: Windows
License-File: LICENSE
Requires-Dist: fastapi
Requires-Dist: openai
Requires-Dist: pydantic
Requires-Dist: python-multipart
Requires-Dist: python-dotenv
Requires-Dist: httpx
Requires-Dist: py-cord[voice]
Requires-Dist: twitter-api-client
Requires-Dist: elevenlabs
